{
  "data": {
    "ticker": "SLAB",
    "current_price": 148.74000549316406,
    "price_52w_high": 160.0,
    "price_52w_low": 82.81999969482422,
    "price_pct_from_52w_high": -7.037496566772461,
    "price_pct_from_52w_low": 79.59430818792852,
    "avg_volume_10d": 349030.0,
    "avg_volume_50d": 283200.0,
    "volume_today": 406900.0,
    "volume_surge_ratio": 1.4367937853107344,
    "ma_50": 133.79759963989258,
    "ma_150": 135.44166600545248,
    "ma_200": 129.73674968719482,
    "price_vs_ma_50": 11.167917730578104,
    "price_vs_ma_150": 9.81849963893402,
    "price_vs_ma_200": 14.647550406332478,
    "ma_50_above_ma_150": false,
    "ma_50_above_ma_200": true,
    "ma_150_above_ma_200": true,
    "market_cap": 4886546944,
    "pe_ratio": null,
    "forward_pe": 54.970398,
    "peg_ratio": null,
    "earnings_growth_qtrly": null,
    "earnings_growth_annual": null,
    "revenue_growth_qtrly": null,
    "revenue_growth_annual": 0.238,
    "profit_margin": -0.115839995,
    "operating_margin": -0.059910003,
    "roe": -0.079959996,
    "institutional_ownership": 1.02686,
    "rs_rating": 49.800796812749006,
    "price_momentum_3m": 9.27926296831707,
    "price_momentum_6m": 1.5983686436040756,
    "atr_14": 5.281700717461225,
    "beta": 1.545,
    "analyst_target_mean": 152.2,
    "analyst_target_low": 130.0,
    "analyst_target_high": 180.0,
    "analyst_target_upside_pct": 2.3262030247773144,
    "analyst_recommendation_mean": 2.27273,
    "analyst_count": 10,
    "recent_upgrades_30d": 0,
    "recent_downgrades_30d": 0,
    "sector": "Technology",
    "industry": "Semiconductors",
    "market_cap_category": "mid",
    "fetched_at": "2026-01-18T23:47:02.715432"
  },
  "timestamp": "2026-01-18T23:47:02.715468",
  "ttl_hours": 24,
  "key": "fundamentals:SLAB"
}