{
  "data": {
    "ticker": "ALGN",
    "current_price": 171.49000549316406,
    "price_52w_high": 237.22999572753906,
    "price_52w_low": 122.0,
    "price_pct_from_52w_high": -27.711499986653465,
    "price_pct_from_52w_low": 40.56557827308529,
    "avg_volume_10d": 975350.0,
    "avg_volume_50d": 1269140.0,
    "volume_today": 1371000.0,
    "volume_surge_ratio": 1.0802590730731045,
    "ma_50": 154.03179901123048,
    "ma_150": 153.76353312174479,
    "ma_200": 159.19564987182616,
    "price_vs_ma_50": 11.334157358417073,
    "price_vs_ma_150": 11.528398191386536,
    "price_vs_ma_200": 7.722796214115468,
    "ma_50_above_ma_150": true,
    "ma_50_above_ma_200": false,
    "ma_150_above_ma_200": false,
    "market_cap": 12430687232,
    "pe_ratio": 33.234497,
    "forward_pe": 15.596607,
    "peg_ratio": null,
    "earnings_growth_qtrly": -0.511,
    "earnings_growth_annual": -0.497,
    "revenue_growth_qtrly": null,
    "revenue_growth_annual": 0.018,
    "profit_margin": 0.095010005,
    "operating_margin": 0.15673,
    "roe": 0.095769994,
    "institutional_ownership": 0.97466004,
    "rs_rating": 46.21513944223107,
    "price_momentum_3m": 31.460336914538267,
    "price_momentum_6m": -9.274150028072391,
    "atr_14": 4.238493774083589,
    "beta": 1.833,
    "analyst_target_mean": 180.46667,
    "analyst_target_low": 150.0,
    "analyst_target_high": 220.0,
    "analyst_target_upside_pct": 5.234511761208008,
    "analyst_recommendation_mean": 2.16667,
    "analyst_count": 15,
    "recent_upgrades_30d": 0,
    "recent_downgrades_30d": 0,
    "sector": "Healthcare",
    "industry": "Medical Instruments & Supplies",
    "market_cap_category": "large",
    "fetched_at": "2026-01-18T23:46:57.264460"
  },
  "timestamp": "2026-01-18T23:46:57.264505",
  "ttl_hours": 24,
  "key": "fundamentals:ALGN"
}